ace/__init__.py
ace/__main__.py
ace/charter.py
auto_chart_engine-1.0.0.dist-info/LICENSE
auto_chart_engine-1.0.0.dist-info/METADATA
auto_chart_engine-1.0.0.dist-info/WHEEL
auto_chart_engine-1.0.0.dist-info/top_level.txt
auto_chart_engine-1.0.0.dist-info/RECORD
