Metadata-Version: 2.1
Name: auto-chart-engine
Version: 1.0.0
Summary: This project streamlines charting for Clone Hero, the free PC rhythm game inspired by Guitar Hero/Rock Band. It generates highly accurate, playable charts directly from audio tracks using advanced extraction techniques like isolating drum tracks from MIDI and extracting precise note data. The engine dramatically reduces the time and effort needed to create custom song charts, enabling efficient creation of multiple songs.
Author: Ryan Roche, Bryant Vencill
Project-URL: Homepage, https://github.com/ryan-w-roche/auto-chart-engine
Classifier: Programming Language :: Python :: 3
Classifier: Development Status :: 4 - Beta
Classifier: Operating System :: OS Independent
Classifier: Topic :: Software Development :: Libraries
Classifier: Intended Audience :: End Users/Desktop
Requires-Python: >=3.8
License-File: LICENSE
